github_org_stats.py
github_org_stats-1.1.0.dist-info/licenses/LICENSE
github_org_stats-1.1.0.dist-info/METADATA
github_org_stats-1.1.0.dist-info/WHEEL
github_org_stats-1.1.0.dist-info/entry_points.txt
github_org_stats-1.1.0.dist-info/top_level.txt
github_org_stats-1.1.0.dist-info/RECORD
