Metadata-Version: 2.4
Name: github-org-stats
Version: 1.1.0
Summary: A comprehensive tool for analyzing GitHub organization statistics
Author-email: Open Source Contributors <contributors@github-org-stats.org>
Project-URL: Homepage, https://github.com/zoharbabin/github-org-stats
Project-URL: Bug Reports, https://github.com/zoharbabin/github-org-stats/issues
Project-URL: Source, https://github.com/zoharbabin/github-org-stats
Project-URL: Documentation, https://github.com/zoharbabin/github-org-stats/blob/main/README.md
Keywords: github,organization,statistics,analysis,repositories,contributors
Classifier: Development Status :: 5 - Production/Stable
Classifier: Intended Audience :: Developers
Classifier: Intended Audience :: System Administrators
Classifier: License :: OSI Approved :: MIT License
Classifier: Operating System :: OS Independent
Classifier: Programming Language :: Python :: 3
Classifier: Programming Language :: Python :: 3.7
Classifier: Programming Language :: Python :: 3.8
Classifier: Programming Language :: Python :: 3.9
Classifier: Programming Language :: Python :: 3.10
Classifier: Programming Language :: Python :: 3.11
Classifier: Programming Language :: Python :: 3.12
Classifier: Topic :: Software Development :: Libraries :: Python Modules
Classifier: Topic :: System :: Systems Administration
Classifier: Topic :: Utilities
Requires-Python: >=3.7
License-File: LICENSE
Requires-Dist: PyGithub>=1.55.0
Requires-Dist: pandas>=1.3.0
Requires-Dist: numpy>=1.21.0
Requires-Dist: requests>=2.25.0
Requires-Dist: PyJWT>=2.0.0
Requires-Dist: tqdm>=4.60.0
Requires-Dist: openpyxl>=3.0.0
Requires-Dist: pytz>=2021.1
Provides-Extra: dev
Requires-Dist: pytest>=6.0.0; extra == "dev"
Requires-Dist: pytest-cov>=2.10.0; extra == "dev"
Requires-Dist: black>=21.0.0; extra == "dev"
Requires-Dist: flake8>=3.8.0; extra == "dev"
Requires-Dist: mypy>=0.800; extra == "dev"
Dynamic: license-file
